matek/__init__.py
matek/osszeadas_kivonas.py
matek/szorzas.py
matek/tests/test_multiplication.py
matek-0.1.4.dist-info/METADATA
matek-0.1.4.dist-info/WHEEL
matek-0.1.4.dist-info/entry_points.txt
matek-0.1.4.dist-info/top_level.txt
matek-0.1.4.dist-info/RECORD
