Metadata-Version: 2.1
Name: matek
Version: 0.1.4
Summary: Matek for the 3rd grade
Home-page: 
Author: Csaba Saranszky
Author-email: alt@256.hu
License: GPL
Requires-Dist: colorama
